CHANGELOG.txt
LICENCE.txt
MANIFEST.in
README.md
setup.py
pys2_msgboxes/__init__.py
pys2_msgboxes/msgboxes.py
pys2_msgboxes.egg-info/PKG-INFO
pys2_msgboxes.egg-info/SOURCES.txt
pys2_msgboxes.egg-info/dependency_links.txt
pys2_msgboxes.egg-info/requires.txt
pys2_msgboxes.egg-info/top_level.txt
pys2_msgboxes/icons/correct.png
pys2_msgboxes/icons/database-error.png
pys2_msgboxes/icons/error.png
pys2_msgboxes/icons/information.png
pys2_msgboxes/icons/input_error.png
pys2_msgboxes/icons/warning.png