Metadata-Version: 2.1
Name: pys2-msgboxes
Version: 0.0.2
Summary: Pre-built Messageboxes for PySide2 Applications
Home-page: https://github.com/StrtCoding/pys2-msgboxes
Author: Straight Coding
Author-email: strtcodingcontact@gmail.com
License: MIT
Keywords: PySide2 QMessageBox pys2-msgboxes
Platform: UNKNOWN
Classifier: Development Status :: 4 - Beta
Classifier: Intended Audience :: Education
Classifier: Operating System :: Microsoft :: Windows :: Windows 10
Classifier: License :: OSI Approved :: MIT License
Classifier: Programming Language :: Python :: 3
